setup.py
radioencode/__init__.py
radioencode.egg-info/PKG-INFO
radioencode.egg-info/SOURCES.txt
radioencode.egg-info/dependency_links.txt
radioencode.egg-info/entry_points.txt
radioencode.egg-info/requires.txt
radioencode.egg-info/top_level.txt