Metadata-Version: 1.0
Name: radioencode
Version: 0.3
Summary: Convert morse code into sound
Home-page: https://github.com/NeverMine17/radioencode
Author: NeverMine17
Author-email: dannevergame@gmail.com
License: MIT
Platform: UNKNOWN
